.coveragerc
.editorconfig
.gitattributes
CHANGES.rst
CONTRIBUTORS.rst
MANIFEST.in
README.rst
bootstrap-buildout.py
buildout.cfg
setup.py
travis.cfg
docs/LICENSE.GPL
docs/LICENSE.rst
docs/index.rst
src/cciaapd/__init__.py
src/cciaapd.portlet.bandi.egg-info/PKG-INFO
src/cciaapd.portlet.bandi.egg-info/SOURCES.txt
src/cciaapd.portlet.bandi.egg-info/dependency_links.txt
src/cciaapd.portlet.bandi.egg-info/entry_points.txt
src/cciaapd.portlet.bandi.egg-info/namespace_packages.txt
src/cciaapd.portlet.bandi.egg-info/not-zip-safe
src/cciaapd.portlet.bandi.egg-info/requires.txt
src/cciaapd.portlet.bandi.egg-info/top_level.txt
src/cciaapd/portlet/__init__.py
src/cciaapd/portlet/bandi/__init__.py
src/cciaapd/portlet/bandi/bando_details_portlet.pt
src/cciaapd/portlet/bandi/bando_details_portlet.py
src/cciaapd/portlet/bandi/configure.zcml
src/cciaapd/portlet/bandi/interfaces.py
src/cciaapd/portlet/bandi/setuphandlers.py
src/cciaapd/portlet/bandi/testing.py
src/cciaapd/portlet/bandi/locales/cciaapd.portlet.bandi.pot
src/cciaapd/portlet/bandi/locales/update.sh
src/cciaapd/portlet/bandi/profiles/default/browserlayer.xml
src/cciaapd/portlet/bandi/profiles/default/cciaapdportletbandi_default.txt
src/cciaapd/portlet/bandi/profiles/default/metadata.xml
src/cciaapd/portlet/bandi/profiles/default/portlets.xml
src/cciaapd/portlet/bandi/tests/__init__.py
src/cciaapd/portlet/bandi/tests/test_robot.py
src/cciaapd/portlet/bandi/tests/test_setup.py
src/cciaapd/portlet/bandi/tests/robot/test_example.robot