Metadata-Version: 2.1
Name: cciaapd.portlet.bandi
Version: 0.2.0
Summary: A portlet for bandi
Home-page: http://pypi.python.org/pypi/cciaapd.portlet.bandi
Author: RedTurtle Technology
Author-email: sviluppoplone@redturtle.it
License: GPL version 2
Keywords: Python Plone
Platform: UNKNOWN
Classifier: Environment :: Web Environment
Classifier: Framework :: Plone
Classifier: Framework :: Plone :: 4.3
Classifier: Programming Language :: Python
Classifier: Programming Language :: Python :: 2.7
Classifier: Operating System :: OS Independent
Classifier: License :: OSI Approved :: GNU General Public License v2 (GPLv2)
Provides-Extra: test
